bupper/__init__.py
bupper/bupper.py
bupper/utils.py
bupper-0.1.2.dist-info/DESCRIPTION.rst
bupper-0.1.2.dist-info/METADATA
bupper-0.1.2.dist-info/RECORD
bupper-0.1.2.dist-info/WHEEL
bupper-0.1.2.dist-info/entry_points.txt
bupper-0.1.2.dist-info/metadata.json
bupper-0.1.2.dist-info/top_level.txt
