Metadata-Version: 2.0
Name: bupper
Version: 0.1.2
Summary: Very simple backup application intended to be run on cron to allow user-controllable remote backups
Home-page: https://github.com/michaelpb/bupper
Author: michaelb
Author-email: michaelpb@gmail.com
License: GPL3
Keywords: bupper
Platform: UNKNOWN
Classifier: Development Status :: 4 - Beta
Classifier: Intended Audience :: Developers
Classifier: Intended Audience :: End Users/Desktop
Classifier: Environment :: Console
Classifier: Natural Language :: English
Classifier: Programming Language :: Python :: 2
Classifier: Programming Language :: Python :: 2.6
Classifier: Programming Language :: Python :: 2.7
Classifier: Programming Language :: Python :: 3
Classifier: Programming Language :: Python :: 3.3
Classifier: Programming Language :: Python :: 3.4
Classifier: Programming Language :: Python :: 3.5
Classifier: Programming Language :: Python :: 3.6
Classifier: Programming Language :: Python :: Implementation :: PyPy
Classifier: License :: OSI Approved :: GNU General Public License v3 or later (GPLv3+)
